rodent/__init__.py
rodent/main.py
rodent_bot-0.0.0.dist-info/METADATA
rodent_bot-0.0.0.dist-info/WHEEL
rodent_bot-0.0.0.dist-info/RECORD
