Metadata-Version: 2.1
Name: rodent-bot
Version: 0.0.0
Summary: Free, open-source discord bot with advanced customization.
License: MIT
Author: Adam Garza
Requires-Python: >=3.11,<4.0
Classifier: License :: OSI Approved :: MIT License
Classifier: Programming Language :: Python :: 3
Classifier: Programming Language :: Python :: 3.11
Classifier: Programming Language :: Python :: 3.12
